Workbook

Sheet Dashboard
A1: Meridian Retail Co. — Budget vs. Actual Variance Dashboard (FY2025)
A2: Drill down on Region_Variance and Department_Variance tabs (conditional formatting flags every exception)
A4: FY2025 Revenue Variance $ | D4: FY2025 Revenue Variance % | G4: FY2025 OpEx Variance $ (Favorable) | J4: FY2025 OpEx Variance % | M4: Flagged Exceptions (Rev + OpEx)
A5: =SUMIF(Region_Variance!A5:A64,"<>")*0+SUM(Region_Variance!E5:E64) -> -2102400.6 | D5: =SUM(Region_Variance!D5:D64)/SUM(Region_Variance!C5:C64)-1 -> -0.10095794 | G5: =-SUM(Department_Variance!E5:E64) -> -275283.5 | J5: =SUM(Department_Variance!D5:D64)/SUM(Department_Variance!C5:C64)-1 -> 0.036160611 | M5: =COUNTIF(Region_Variance!G5:G64,"FLAG")+COUNTIF(Department_Variance!G5:G64,"OVERSPEND")+COUNTIF(Department_Variance!G5:G64,"UNDERSPEND") -> 85
A7: Revenue: Budget vs. Actual by Region (FY2025 Full Year) | F7: OpEx: Budget vs. Actual by Department (FY2025 Full Year)
A8: Region | B8: Budget | C8: Actual | D8: Variance % | F8: Department | G8: Budget | H8: Actual | I8: Variance %
A9: APAC | B9: =SUMIF(Region_Variance!$A$5:$A$64,A9,Region_Variance!$C$5:$C$64) -> 2750450 | C9: =SUMIF(Region_Variance!$A$5:$A$64,A9,Region_Variance!$D$5:$D$64) -> 2573786.8 | D9: =C9/B9-1 -> -0.06423066 | F9: Customer Support | G9: =SUMIF(Department_Variance!$A$5:$A$64,F9,Department_Variance!$C$5:$C$64) -> 879000 | H9: =SUMIF(Department_Variance!$A$5:$A$64,F9,Department_Variance!$D$5:$D$64) -> 791100 | I9: =H9/G9-1 -> -0.1
A10: Europe | B10: =SUMIF(Region_Variance!$A$5:$A$64,A10,Region_Variance!$C$5:$C$64) -> 5090424.4 | C10: =SUMIF(Region_Variance!$A$5:$A$64,A10,Region_Variance!$D$5:$D$64) -> 4548997.2 | D10: =C10/B10-1 -> -0.10636189 | F10: General & Administrative | G10: =SUMIF(Department_Variance!$A$5:$A$64,F10,Department_Variance!$C$5:$C$64) -> 1080000 | H10: =SUMIF(Department_Variance!$A$5:$A$64,F10,Department_Variance!$D$5:$D$64) -> 1206360 | I10: =H10/G10-1 -> 0.117
A11: Greater Asia | B11: =SUMIF(Region_Variance!$A$5:$A$64,A11,Region_Variance!$C$5:$C$64) -> 5480465.2 | C11: =SUMIF(Region_Variance!$A$5:$A$64,A11,Region_Variance!$D$5:$D$64) -> 3096550.1 | D11: =C11/B11-1 -> -0.43498408 | F11: Operations & Logistics | G11: =SUMIF(Department_Variance!$A$5:$A$64,F11,Department_Variance!$C$5:$C$64) -> 1685400 | H11: =SUMIF(Department_Variance!$A$5:$A$64,F11,Department_Variance!$D$5:$D$64) -> 1715672 | I11: =H11/G11-1 -> 0.017961315
A12: Latin America | B12: =SUMIF(Region_Variance!$A$5:$A$64,A12,Region_Variance!$C$5:$C$64) -> 1201255.8 | C12: =SUMIF(Region_Variance!$A$5:$A$64,A12,Region_Variance!$D$5:$D$64) -> 1408055.2 | D12: =C12/B12-1 -> 0.17215273 | F12: Research & Development | G12: =SUMIF(Department_Variance!$A$5:$A$64,F12,Department_Variance!$C$5:$C$64) -> 1502400 | H12: =SUMIF(Department_Variance!$A$5:$A$64,F12,Department_Variance!$D$5:$D$64) -> 1496244 | I12: =H12/G12-1 -> -0.0040974441
A13: North America | B13: =SUMIF(Region_Variance!$A$5:$A$64,A13,Region_Variance!$C$5:$C$64) -> 6301924 | C13: =SUMIF(Region_Variance!$A$5:$A$64,A13,Region_Variance!$D$5:$D$64) -> 7094729.5 | D13: =C13/B13-1 -> 0.12580371 | F13: Sales & Marketing | G13: =SUMIF(Department_Variance!$A$5:$A$64,F13,Department_Variance!$C$5:$C$64) -> 2466000 | H13: =SUMIF(Department_Variance!$A$5:$A$64,F13,Department_Variance!$D$5:$D$64) -> 2678707.5 | I13: =H13/G13-1 -> 0.086256083
A35: Headline insight: the FY2025 plan assumed a uniform +10% revenue lift across every region. Greater Asia missed that plan by -43.5% while North America beat it by +12.6% — a single region's miss erased most of the company's outperformance elsewhere. On the cost side, G&A overspend crept up every single month without ever triggering a single-month alarm — exactly the kind of slow-creep variance a monthly review (instead of only an annual one) is built to catch.

Sheet Region_Variance
A1: Revenue Variance by Region x Month — FY2025
A2: Budget = FY2024 actual x planned +10% growth, set before the year started. Source: SQL export.
A4: Region | B4: Month | C4: Budget | D4: Actual | E4: Variance $ | F4: Variance % | G4: Exception
A5: APAC | B5: 1 | C5: 261292.94 | D5: 293073.61 | E5: =D5-C5 -> 31780.67 | F5: =D5/C5-1 -> 0.12162851 | G5: =IF(ABS(F5)>0.1,"FLAG","") -> FLAG
A6: APAC | B6: 2 | C6: 107863.45 | D6: 192400.57 | E6: =D6-C6 -> 84537.12 | F6: =D6/C6-1 -> 0.78374204 | G6: =IF(ABS(F6)>0.1,"FLAG","") -> FLAG
A7: APAC | B7: 3 | C7: 184974.34 | D7: 164869.57 | E7: =D7-C7 -> -20104.77 | F7: =D7/C7-1 -> -0.10868951 | G7: =IF(ABS(F7)>0.1,"FLAG","") -> FLAG
A8: APAC | B8: 4 | C8: 306779.32 | D8: 88496.75 | E8: =D8-C8 -> -218282.57 | F8: =D8/C8-1 -> -0.71152961 | G8: =IF(ABS(F8)>0.1,"FLAG","") -> FLAG
A9: APAC | B9: 5 | C9: 205260.92 | D9: 245857.41 | E9: =D9-C9 -> 40596.49 | F9: =D9/C9-1 -> 0.19777993 | G9: =IF(ABS(F9)>0.1,"FLAG","") -> FLAG
A10: APAC | B10: 6 | C10: 183481.97 | D10: 176163.74 | E10: =D10-C10 -> -7318.23 | F10: =D10/C10-1 -> -0.039885281 | G10: =IF(ABS(F10)>0.1,"FLAG","")
A11: APAC | B11: 7 | C11: 240193.54 | D11: 150713.95 | E11: =D11-C11 -> -89479.59 | F11: =D11/C11-1 -> -0.37253121 | G11: =IF(ABS(F11)>0.1,"FLAG","") -> FLAG
A12: APAC | B12: 8 | C12: 158139.84 | D12: 134207.61 | E12: =D12-C12 -> -23932.23 | F12: =D12/C12-1 -> -0.15133587 | G12: =IF(ABS(F12)>0.1,"FLAG","") -> FLAG
A13: APAC | B13: 9 | C13: 191172.2 | D13: 250566.97 | E13: =D13-C13 -> 59394.77 | F13: =D13/C13-1 -> 0.31068728 | G13: =IF(ABS(F13)>0.1,"FLAG","") -> FLAG
A14: APAC | B14: 10 | C14: 274540.73 | D14: 219938.82 | E14: =D14-C14 -> -54601.91 | F14: =D14/C14-1 -> -0.19888455 | G14: =IF(ABS(F14)>0.1,"FLAG","") -> FLAG
A15: APAC | B15: 11 | C15: 281396.1 | D15: 309874.44 | E15: =D15-C15 -> 28478.34 | F15: =D15/C15-1 -> 0.10120375 | G15: =IF(ABS(F15)>0.1,"FLAG","") -> FLAG
A16: APAC | B16: 12 | C16: 355354.68 | D16: 347623.37 | E16: =D16-C16 -> -7731.31 | F16: =D16/C16-1 -> -0.021756601 | G16: =IF(ABS(F16)>0.1,"FLAG","")
... A64: North America | B64: 12 | C64: 852424.45 | D64: 1222879.1 | E64: =D64-C64 -> 370454.69 | F64: =D64/C64-1 -> 0.43458947 | G64: =IF(ABS(F64)>0.1,"FLAG","") -> FLAG

Sheet Department_Variance
A1: OpEx Variance by Department x Month — FY2025
A2: Positive variance % = overspend vs. budget (unfavorable). Source: SQL export.
A4: Department | B4: Month | C4: Budget | D4: Actual | E4: Variance $ | F4: Variance % | G4: Exception
A5: Customer Support | B5: 1 | C5: 70500 | D5: 63450 | E5: =D5-C5 -> -7050 | F5: =D5/C5-1 -> -0.1 | G5: =IF(F5>0.05,"OVERSPEND",IF(F5<-0.05,"UNDERSPEND","")) -> UNDERSPEND
A6: Customer Support | B6: 2 | C6: 71000 | D6: 63900 | E6: =D6-C6 -> -7100 | F6: =D6/C6-1 -> -0.1 | G6: =IF(F6>0.05,"OVERSPEND",IF(F6<-0.05,"UNDERSPEND","")) -> UNDERSPEND
A7: Customer Support | B7: 3 | C7: 71500 | D7: 64350 | E7: =D7-C7 -> -7150 | F7: =D7/C7-1 -> -0.1 | G7: =IF(F7>0.05,"OVERSPEND",IF(F7<-0.05,"UNDERSPEND","")) -> UNDERSPEND
A8: Customer Support | B8: 4 | C8: 72000 | D8: 64800 | E8: =D8-C8 -> -7200 | F8: =D8/C8-1 -> -0.1 | G8: =IF(F8>0.05,"OVERSPEND",IF(F8<-0.05,"UNDERSPEND","")) -> UNDERSPEND
A9: Customer Support | B9: 5 | C9: 72500 | D9: 65250 | E9: =D9-C9 -> -7250 | F9: =D9/C9-1 -> -0.1 | G9: =IF(F9>0.05,"OVERSPEND",IF(F9<-0.05,"UNDERSPEND","")) -> UNDERSPEND
A10: Customer Support | B10: 6 | C10: 73000 | D10: 65700 | E10: =D10-C10 -> -7300 | F10: =D10/C10-1 -> -0.1 | G10: =IF(F10>0.05,"OVERSPEND",IF(F10<-0.05,"UNDERSPEND","")) -> UNDERSPEND
A11: Customer Support | B11: 7 | C11: 73500 | D11: 66150 | E11: =D11-C11 -> -7350 | F11: =D11/C11-1 -> -0.1 | G11: =IF(F11>0.05,"OVERSPEND",IF(F11<-0.05,"UNDERSPEND","")) -> UNDERSPEND
A12: Customer Support | B12: 8 | C12: 74000 | D12: 66600 | E12: =D12-C12 -> -7400 | F12: =D12/C12-1 -> -0.1 | G12: =IF(F12>0.05,"OVERSPEND",IF(F12<-0.05,"UNDERSPEND","")) -> UNDERSPEND
A13: Customer Support | B13: 9 | C13: 74500 | D13: 67050 | E13: =D13-C13 -> -7450 | F13: =D13/C13-1 -> -0.1 | G13: =IF(F13>0.05,"OVERSPEND",IF(F13<-0.05,"UNDERSPEND","")) -> UNDERSPEND
A14: Customer Support | B14: 10 | C14: 75000 | D14: 67500 | E14: =D14-C14 -> -7500 | F14: =D14/C14-1 -> -0.1 | G14: =IF(F14>0.05,"OVERSPEND",IF(F14<-0.05,"UNDERSPEND","")) -> UNDERSPEND
A15: Customer Support | B15: 11 | C15: 75500 | D15: 67950 | E15: =D15-C15 -> -7550 | F15: =D15/C15-1 -> -0.1 | G15: =IF(F15>0.05,"OVERSPEND",IF(F15<-0.05,"UNDERSPEND","")) -> UNDERSPEND
A16: Customer Support | B16: 12 | C16: 76000 | D16: 68400 | E16: =D16-C16 -> -7600 | F16: =D16/C16-1 -> -0.1 | G16: =IF(F16>0.05,"OVERSPEND",IF(F16<-0.05,"UNDERSPEND","")) -> UNDERSPEND
... A64: Sales & Marketing | B64: 12 | C64: 249000 | D64: 328680 | E64: =D64-C64 -> 79680 | F64: =D64/C64-1 -> 0.32 | G64: =IF(F64>0.05,"OVERSPEND",IF(F64<-0.05,"UNDERSPEND","")) -> OVERSPEND
